django_request_logging/__init__.py
django_request_logging/admin.py
django_request_logging/apps.py
django_request_logging/middleware.py
django_request_logging/models.py
django_request_logging/migrations/0001_initial.py
django_request_logging/migrations/__init__.py
django_api_request_logging-0.3.0.dist-info/LICENSE
django_api_request_logging-0.3.0.dist-info/METADATA
django_api_request_logging-0.3.0.dist-info/WHEEL
django_api_request_logging-0.3.0.dist-info/top_level.txt
django_api_request_logging-0.3.0.dist-info/RECORD
